odoo/addons/project_tree_view/__init__.py
odoo/addons/project_tree_view/__manifest__.py
odoo/addons/project_tree_view/views/project_tree_view.xml
odoo12_addon_project_tree_view-12.0.1.0.0.99.dev1.dist-info/METADATA
odoo12_addon_project_tree_view-12.0.1.0.0.99.dev1.dist-info/WHEEL
odoo12_addon_project_tree_view-12.0.1.0.0.99.dev1.dist-info/top_level.txt
odoo12_addon_project_tree_view-12.0.1.0.0.99.dev1.dist-info/RECORD
